{
    "keep": {
        "days": true,
        "amount": 14
    },
    "auditLog": "D:\\next-level\\job portal\\server\\logs\\winston\\successes\\.e5dc61837ad8e732ce8ffb1d70e70644f9fd7764-audit.json",
    "files": [
        {
            "date": 1692621207617,
            "name": "D:\\next-level\\job portal\\server\\logs\\winston\\successes\\phu-2023-21-08-20-success.log",
            "hash": "78d752ff13339ff47dbeb18d24e92c76eada477bc67ab7832c7c1b56a18c1f6d"
        },
        {
            "date": 1692629452781,
            "name": "D:\\next-level\\job portal\\server\\logs\\winston\\successes\\phu-2023-21-08-22-success.log",
            "hash": "9dc3b4ddc0af7545ae7cc0d4aab0e7d48dea4a81eebcdce314945c6ad7ccc7f6"
        },
        {
            "date": 1692630790511,
            "name": "D:\\next-level\\job portal\\server\\logs\\winston\\successes\\phu-2023-21-08-23-success.log",
            "hash": "1ddb65f179914d92410ea6f492cb9434ac801a8497961faa4b4caa8993622c66"
        },
        {
            "date": 1692633650073,
            "name": "D:\\next-level\\job portal\\server\\logs\\winston\\successes\\phu-2023-22-08-00-success.log",
            "hash": "1dd1b00764a420433f7be3efb020099bfb5bcaa4424000b637e352a7fb83cf01"
        },
        {
            "date": 1692637508181,
            "name": "D:\\next-level\\job portal\\server\\logs\\winston\\successes\\phu-2023-22-08-01-success.log",
            "hash": "8e5df122078629274b04c2c3dc9c27426e81502bfa59270bbc305ea3c0e89255"
        },
        {
            "date": 1692640855100,
            "name": "D:\\next-level\\job portal\\server\\logs\\winston\\successes\\phu-2023-22-08-02-success.log",
            "hash": "0334e4b381c33409bbc1da2c9ea61da2c4944c040536d22b1cd632a8fe60b6ac"
        },
        {
            "date": 1692672719680,
            "name": "D:\\next-level\\job portal\\server\\logs\\winston\\successes\\phu-2023-22-08-10-success.log",
            "hash": "27bc22fec5672483270ce86d3f1dfc97462f829fb62270580c02d28716443b50"
        },
        {
            "date": 1692673470397,
            "name": "D:\\next-level\\job portal\\server\\logs\\winston\\successes\\phu-2023-22-08-11-success.log",
            "hash": "86d93c10753183f7714faaf5d51fa2b1c933bbb0964c8a1cba4ba6c6007c9505"
        },
        {
            "date": 1692677656977,
            "name": "D:\\next-level\\job portal\\server\\logs\\winston\\successes\\phu-2023-22-08-12-success.log",
            "hash": "592cd72ecdc9621c52057e3dfe2f04a7f52ca585c55d1470ba87aa3c39af9051"
        },
        {
            "date": 1692695716258,
            "name": "D:\\next-level\\job portal\\server\\logs\\winston\\successes\\phu-2023-22-08-17-success.log",
            "hash": "4f893f560364c4d190fba85efe926eaf32bab06430e7347e2a6c58e8da82a051"
        },
        {
            "date": 1692698542289,
            "name": "D:\\next-level\\job portal\\server\\logs\\winston\\successes\\phu-2023-22-08-18-success.log",
            "hash": "fecce5609a39d49fdd983b3caf13bd052ed0b2497a6e0428a51729f538245b9e"
        },
        {
            "date": 1692702076025,
            "name": "D:\\next-level\\job portal\\server\\logs\\winston\\successes\\phu-2023-22-08-19-success.log",
            "hash": "0b47aa55c851e6e89e9c866c70ec977bb6ecd98fbe321f41f6b222071dcfcd4d"
        },
        {
            "date": 1692705831875,
            "name": "D:\\next-level\\job portal\\server\\logs\\winston\\successes\\phu-2023-22-08-20-success.log",
            "hash": "048e036c7294ef7ca2b55f96b3b06b2b5f167653ace384789846f4ad493e16d3"
        },
        {
            "date": 1692713821055,
            "name": "D:\\next-level\\job portal\\server\\logs\\winston\\successes\\phu-2023-22-08-22-success.log",
            "hash": "533fa5b2e980a1ebf9b45d6baf034a9db75eac93ce0978c7aa7648ae9d88195d"
        },
        {
            "date": 1692716493491,
            "name": "D:\\next-level\\job portal\\server\\logs\\winston\\successes\\phu-2023-22-08-23-success.log",
            "hash": "256fca26fcfcc9ac1c4e892174ab5ee94886e6ff92d9f56dc4600d0a6a03e44e"
        },
        {
            "date": 1692721074000,
            "name": "D:\\next-level\\job portal\\server\\logs\\winston\\successes\\phu-2023-23-08-00-success.log",
            "hash": "f48730a3439d19fe486447a05db070adff138f5a77e0ea6171fb002d896b7635"
        }
    ],
    "hashType": "sha256"
}